gggdtparser/__init__.py
gggdtparser/dtconfigs.py
gggdtparser/dtframe.py
gggdtparser/dtparser.py
gggdtparser/utils.py
gggdtparser/langs/__init__.py
gggdtparser/langs/_id.py
gggdtparser/langs/az.py
gggdtparser/langs/de.py
gggdtparser/langs/default.py
gggdtparser/langs/en.py
gggdtparser/langs/es.py
gggdtparser/langs/fra.py
gggdtparser/langs/hi.py
gggdtparser/langs/ja.py
gggdtparser/langs/ky.py
gggdtparser/langs/mr.py
gggdtparser/langs/ru.py
gggdtparser/langs/rw.py
gggdtparser/langs/si.py
gggdtparser/langs/so.py
gggdtparser/langs/sw.py
gggdtparser/langs/swe.py
gggdtparser/langs/tg.py
gggdtparser/langs/tr.py
gggdtparser/langs/uk.py
gggdtparser/langs/ur.py
gggdtparser/langs/vie.py
gggdtparser/langs/zh.py
gggdtparser/langs/zht.py
gggdtparser/test/__init__.py
gggdtparser/test/_id.py
gggdtparser/test/az.py
gggdtparser/test/hi.py
gggdtparser/test/ky.py
gggdtparser/test/mr.py
gggdtparser/test/ru.py
gggdtparser/test/rw.py
gggdtparser/test/si.py
gggdtparser/test/sw.py
gggdtparser/test/tg.py
gggdtparser/test/tr.py
gggdtparser/test/uk.py
gggdtparser/test/ur.py
gggdtparser-0.1.6.dist-info/LICENSE
gggdtparser-0.1.6.dist-info/METADATA
gggdtparser-0.1.6.dist-info/WHEEL
gggdtparser-0.1.6.dist-info/top_level.txt
gggdtparser-0.1.6.dist-info/RECORD
