Metadata-Version: 2.1
Name: gggdtparser
Version: 0.1.6
Summary: 通用、便捷、准确的字符串时间解析工具
Home-page: https://github.com/kusen-alpha/gggdtparser
Author: kusen
Author-email: 1194542196@qq.com
License: MIT
Project-URL: Bug Tracker, https://github.com/kusen-alpha/gggdtparser/issues
Project-URL: Documentation, https://github.com/kusen-alpha/gggdtparser/blob/master/README.md
Project-URL: Source Code, https://github.com/kusen-alpha/gggdtparser
Platform: any
Classifier: Programming Language :: Python :: 3
Classifier: License :: OSI Approved :: MIT License
Classifier: Operating System :: OS Independent
License-File: LICENSE
